integrail_sdk/__init__.py
integrail_sdk/api/__init__.py
integrail_sdk/api/base.py
integrail_sdk/api/cloud/__init__.py
integrail_sdk/api/cloud/agent.py
integrail_sdk/api/cloud/execution.py
integrail_sdk/api/cloud/memory.py
integrail_sdk/api/cloud/node.py
integrail_sdk/api/common/__init__.py
integrail_sdk/api/common/agent.py
integrail_sdk/helpers/__init__.py
integrail_sdk/helpers/jsonl.py
integrail_sdk/types/__init__.py
integrail_sdk/types/account.py
integrail_sdk/types/agent.py
integrail_sdk/types/category.py
integrail_sdk/types/chat_message.py
integrail_sdk/types/data.py
integrail_sdk/types/embedding.py
integrail_sdk/types/execution.py
integrail_sdk/types/fail_mode.py
integrail_sdk/types/input.py
integrail_sdk/types/media.py
integrail_sdk/types/node.py
integrail_sdk/types/node_definition.py
integrail_sdk/types/node_execution.py
integrail_sdk/types/output.py
integrail_sdk/types/stats.py
integrail_sdk/types/value.py
integrail_sdk/types/vector_memory.py
integrail_sdk-0.1.1.dist-info/LICENSE.txt
integrail_sdk-0.1.1.dist-info/METADATA
integrail_sdk-0.1.1.dist-info/WHEEL
integrail_sdk-0.1.1.dist-info/RECORD
