Metadata-Version: 2.1
Name: integrail-sdk
Version: 0.1.1
Summary: 
Author: Your Name
Author-email: you@example.com
Requires-Python: >=3.12,<4.0
Classifier: Programming Language :: Python :: 3
Classifier: Programming Language :: Python :: 3.12
Classifier: Programming Language :: Python :: 3.13
Requires-Dist: aiohttp (>=3.10.6,<4.0.0)
Requires-Dist: pydantic (>=2.9.2,<3.0.0)
